pytwitchplays/__init__.py
pytwitchplays/action.py
pytwitchplays/di_keyboard_scan_codes.py
pytwitchplays/direct_input.py
pytwitchplays/py_twitch_plays.py
pytwitchplays-0.1.0.dist-info/LICENSE
pytwitchplays-0.1.0.dist-info/METADATA
pytwitchplays-0.1.0.dist-info/WHEEL
pytwitchplays-0.1.0.dist-info/top_level.txt
pytwitchplays-0.1.0.dist-info/RECORD
