Metadata-Version: 2.1
Name: pytwitchplays
Version: 0.1.0
Summary: Python package to create your own Twitch Plays channel
Home-page: https://github.com/benjiJanssens/PyTwitchPlays
Author: Benjamin Janssens
Author-email: benji.janssens@gmail.com
License: UNKNOWN
Platform: UNKNOWN
Classifier: Programming Language :: Python :: 3
Classifier: License :: OSI Approved :: MIT License
Classifier: Operating System :: OS Independent
Requires-Python: >=3.6
Requires-Dist: pytwitchchat
